{
    "sourceFile": "css/styles.css",
    "activeCommit": 0,
    "commits": [
        {
            "activePatchIndex": 9,
            "patches": [
                {
                    "date": 1753046481037,
                    "content": "Index: \n===================================================================\n--- \n+++ \n"
                },
                {
                    "date": 1753046852123,
                    "content": "Index: \n===================================================================\n--- \n+++ \n@@ -1,39 +1,36 @@\n-/* Reset some default styles */\r\n+/* Reset default browser styles */\r\n * {\r\n     margin: 0;\r\n     padding: 0;\r\n     box-sizing: border-box;\r\n-    font-family: Arial, sans-serif;\r\n+    font-family: 'Segoe UI', Tahoma, Geneva, Verdana, sans-serif;\r\n }\r\n \r\n body {\r\n-    background-color: #f0f2f5;\r\n+    background-color: #f7f9fc;\r\n     color: #333;\r\n }\r\n \r\n #container {\r\n     max-width: 600px;\r\n     margin: 40px auto;\r\n-    padding: 20px;\r\n-    background-color: #fff;\r\n+    padding: 20px 30px;\r\n+    background-color: #ffffff;\r\n     border-radius: 12px;\r\n-    box-shadow: 0 2px 8px rgba(0,0,0,0.1);\r\n+    box-shadow: 0 4px 10px rgba(0,0,0,0.08);\r\n }\r\n \r\n header#hd {\r\n     text-align: center;\r\n-    margin-bottom: 20px;\r\n+    margin-bottom: 25px;\r\n }\r\n \r\n #logo {\r\n-    width: 120px;\r\n+    width: 130px;\r\n }\r\n \r\n-.mn__sect {\r\n-    margin-bottom: 20px;\r\n-}\r\n-\r\n+/* Task Input Section */\r\n #task-input {\r\n     width: 70%;\r\n     padding: 10px;\r\n     border: 1px solid #ccc;\r\n@@ -43,20 +40,27 @@\n \r\n #add-task-btn {\r\n     padding: 10px 15px;\r\n     background-color: #007bff;\r\n-    color: white;\r\n+    color: #fff;\r\n     border: none;\r\n     font-size: 16px;\r\n     border-radius: 6px;\r\n     cursor: pointer;\r\n     margin-left: 10px;\r\n+    transition: background-color 0.3s ease;\r\n }\r\n \r\n #add-task-btn:hover {\r\n     background-color: #0056b3;\r\n }\r\n \r\n+/* Tasks Section */\r\n+.mn__sect h2 {\r\n+    font-size: 22px;\r\n+    margin-bottom: 10px;\r\n+}\r\n+\r\n #task-list {\r\n     list-style-type: decimal;\r\n     padding-left: 20px;\r\n }\r\n@@ -64,41 +68,56 @@\n .task-item {\r\n     display: flex;\r\n     justify-content: space-between;\r\n     align-items: center;\r\n-    padding: 8px 0;\r\n-    border-bottom: 1px solid #eee;\r\n+    padding: 10px 5px;\r\n+    border-bottom: 1px solid #e4e4e4;\r\n }\r\n \r\n .task-item span {\r\n     flex-grow: 1;\r\n+    font-size: 17px;\r\n }\r\n \r\n+/* Completed task style */\r\n .completed span {\r\n     text-decoration: line-through;\r\n-    color: gray;\r\n+    color: #6c757d;\r\n }\r\n \r\n+/* Buttons inside task items */\r\n .complete-btn,\r\n .remove-btn {\r\n     margin-left: 10px;\r\n-    padding: 5px 10px;\r\n+    padding: 6px 10px;\r\n     font-size: 14px;\r\n     border: none;\r\n     border-radius: 4px;\r\n     cursor: pointer;\r\n+    transition: background-color 0.3s ease;\r\n }\r\n \r\n+/* Complete button styling */\r\n .complete-btn {\r\n     background-color: #28a745;\r\n     color: white;\r\n }\r\n \r\n+.complete-btn:hover {\r\n+    background-color: #1e7e34;\r\n+}\r\n+\r\n+/* Remove button styling */\r\n .remove-btn {\r\n     background-color: #dc3545;\r\n     color: white;\r\n }\r\n \r\n+.remove-btn:hover {\r\n+    background-color: #c82333;\r\n+}\r\n+\r\n+/* Footer */\r\n footer#ft {\r\n     text-align: center;\r\n     font-size: 14px;\r\n     margin-top: 30px;\r\n"
                },
                {
                    "date": 1753047225525,
                    "content": "Index: \n===================================================================\n--- \n+++ \n@@ -1,64 +1,66 @@\n-/* Reset default browser styles */\r\n+/* Reset default styles */\r\n * {\r\n     margin: 0;\r\n     padding: 0;\r\n     box-sizing: border-box;\r\n-    font-family: 'Segoe UI', Tahoma, Geneva, Verdana, sans-serif;\r\n+    font-family: 'Comic Neue', 'Segoe UI', sans-serif;\r\n }\r\n \r\n body {\r\n-    background-color: #f7f9fc;\r\n+    background-color: #FFF7E9;\r\n     color: #333;\r\n }\r\n \r\n #container {\r\n     max-width: 600px;\r\n     margin: 40px auto;\r\n-    padding: 20px 30px;\r\n-    background-color: #ffffff;\r\n-    border-radius: 12px;\r\n-    box-shadow: 0 4px 10px rgba(0,0,0,0.08);\r\n+    padding: 25px;\r\n+    background-color: #FFFBF5;\r\n+    border-radius: 16px;\r\n+    box-shadow: 0 5px 15px rgba(0,0,0,0.1);\r\n }\r\n \r\n header#hd {\r\n     text-align: center;\r\n     margin-bottom: 25px;\r\n }\r\n \r\n #logo {\r\n-    width: 130px;\r\n+    width: 120px;\r\n }\r\n \r\n-/* Task Input Section */\r\n+/* Task input section */\r\n #task-input {\r\n     width: 70%;\r\n     padding: 10px;\r\n-    border: 1px solid #ccc;\r\n-    border-radius: 6px;\r\n+    border: 2px solid #FFB6B6;\r\n+    border-radius: 8px;\r\n     font-size: 16px;\r\n+    background-color: #fff;\r\n }\r\n \r\n #add-task-btn {\r\n     padding: 10px 15px;\r\n-    background-color: #007bff;\r\n-    color: #fff;\r\n+    background-color: #FF6B6B;\r\n+    color: white;\r\n     border: none;\r\n     font-size: 16px;\r\n-    border-radius: 6px;\r\n+    border-radius: 8px;\r\n     cursor: pointer;\r\n     margin-left: 10px;\r\n     transition: background-color 0.3s ease;\r\n }\r\n \r\n #add-task-btn:hover {\r\n-    background-color: #0056b3;\r\n+    background-color: #FF4B5C;\r\n }\r\n \r\n-/* Tasks Section */\r\n+/* Task list styling */\r\n .mn__sect h2 {\r\n     font-size: 22px;\r\n     margin-bottom: 10px;\r\n+    color: #FF6B6B;\r\n }\r\n \r\n #task-list {\r\n     list-style-type: decimal;\r\n@@ -69,20 +71,21 @@\n     display: flex;\r\n     justify-content: space-between;\r\n     align-items: center;\r\n     padding: 10px 5px;\r\n-    border-bottom: 1px solid #e4e4e4;\r\n+    border-bottom: 1px dashed #FFD93D;\r\n }\r\n \r\n .task-item span {\r\n     flex-grow: 1;\r\n-    font-size: 17px;\r\n+    font-size: 18px;\r\n }\r\n \r\n /* Completed task style */\r\n .completed span {\r\n     text-decoration: line-through;\r\n-    color: #6c757d;\r\n+    color: #999;\r\n+    opacity: 0.7;\r\n }\r\n \r\n /* Buttons inside task items */\r\n .complete-btn,\r\n@@ -90,36 +93,37 @@\n     margin-left: 10px;\r\n     padding: 6px 10px;\r\n     font-size: 14px;\r\n     border: none;\r\n-    border-radius: 4px;\r\n+    border-radius: 6px;\r\n     cursor: pointer;\r\n-    transition: background-color 0.3s ease;\r\n+    transition: all 0.2s ease;\r\n }\r\n \r\n-/* Complete button styling */\r\n+/* Complete button - green */\r\n .complete-btn {\r\n-    background-color: #28a745;\r\n+    background-color: #6BCB77;\r\n     color: white;\r\n }\r\n \r\n .complete-btn:hover {\r\n-    background-color: #1e7e34;\r\n+    background-color: #4CAF50;\r\n }\r\n \r\n-/* Remove button styling */\r\n+/* Remove button - yellow */\r\n .remove-btn {\r\n-    background-color: #dc3545;\r\n-    color: white;\r\n+    background-color: #FFD93D;\r\n+    color: #333;\r\n }\r\n \r\n .remove-btn:hover {\r\n-    background-color: #c82333;\r\n+    background-color: #FEC601;\r\n }\r\n \r\n /* Footer */\r\n footer#ft {\r\n     text-align: center;\r\n     font-size: 14px;\r\n     margin-top: 30px;\r\n-    color: #666;\r\n+    color: #888;\r\n }\r\n+\r\n"
                },
                {
                    "date": 1753048393020,
                    "content": "Index: \n===================================================================\n--- \n+++ \n@@ -1,129 +1,236 @@\n-/* Reset default styles */\r\n+/* Reset & base */\r\n * {\r\n-    margin: 0;\r\n-    padding: 0;\r\n-    box-sizing: border-box;\r\n-    font-family: 'Comic Neue', 'Segoe UI', sans-serif;\r\n+  margin: 0;\r\n+  padding: 0;\r\n+  box-sizing: border-box;\r\n+  font-family: 'Comic Neue', 'Segoe UI', sans-serif;\r\n }\r\n \r\n body {\r\n-    background-color: #FFF7E9;\r\n-    color: #333;\r\n+  background-color: #FFF7E9;\r\n+  color: #333;\r\n }\r\n \r\n #container {\r\n-    max-width: 600px;\r\n-    margin: 40px auto;\r\n-    padding: 25px;\r\n-    background-color: #FFFBF5;\r\n-    border-radius: 16px;\r\n-    box-shadow: 0 5px 15px rgba(0,0,0,0.1);\r\n+  max-width: 600px;\r\n+  margin: 40px auto;\r\n+  padding: 25px;\r\n+  background-color: #FFFBF5;\r\n+  border-radius: 16px;\r\n+  box-shadow: 0 5px 15px rgba(0,0,0,0.1);\r\n+  transition: background-color 0.3s ease, color 0.3s ease;\r\n }\r\n \r\n+/* Header */\r\n header#hd {\r\n-    text-align: center;\r\n-    margin-bottom: 25px;\r\n+  display: flex;\r\n+  align-items: center;\r\n+  justify-content: center;\r\n+  gap: 15px;\r\n+  margin-bottom: 25px;\r\n }\r\n \r\n #logo {\r\n-    width: 120px;\r\n+  width: 120px;\r\n }\r\n \r\n-/* Task input section */\r\n+#dark-mode-toggle {\r\n+  background: none;\r\n+  border: none;\r\n+  cursor: pointer;\r\n+  font-size: 28px;\r\n+  color: #FF6B6B;\r\n+  transition: color 0.3s ease;\r\n+}\r\n+\r\n+#dark-mode-toggle:hover {\r\n+  color: #FF4B5C;\r\n+}\r\n+\r\n+/* Input and button */\r\n #task-input {\r\n-    width: 70%;\r\n-    padding: 10px;\r\n-    border: 2px solid #FFB6B6;\r\n-    border-radius: 8px;\r\n-    font-size: 16px;\r\n-    background-color: #fff;\r\n+  width: 70%;\r\n+  padding: 10px;\r\n+  border: 2px solid #FFB6B6;\r\n+  border-radius: 8px;\r\n+  font-size: 16px;\r\n+  background-color: #fff;\r\n+  color: #333;\r\n+  transition: border-color 0.3s ease;\r\n }\r\n \r\n+#task-input:focus {\r\n+  border-color: #FF6B6B;\r\n+  outline: none;\r\n+}\r\n+\r\n #add-task-btn {\r\n-    padding: 10px 15px;\r\n-    background-color: #FF6B6B;\r\n-    color: white;\r\n-    border: none;\r\n-    font-size: 16px;\r\n-    border-radius: 8px;\r\n-    cursor: pointer;\r\n-    margin-left: 10px;\r\n-    transition: background-color 0.3s ease;\r\n+  padding: 10px 15px;\r\n+  background-color: #FF6B6B;\r\n+  color: white;\r\n+  border: none;\r\n+  font-size: 16px;\r\n+  border-radius: 8px;\r\n+  cursor: pointer;\r\n+  margin-left: 10px;\r\n+  transition: background-color 0.3s ease;\r\n }\r\n \r\n #add-task-btn:hover {\r\n-    background-color: #FF4B5C;\r\n+  background-color: #FF4B5C;\r\n }\r\n \r\n-/* Task list styling */\r\n+/* Sections */\r\n .mn__sect h2 {\r\n-    font-size: 22px;\r\n-    margin-bottom: 10px;\r\n-    color: #FF6B6B;\r\n+  font-size: 22px;\r\n+  margin-bottom: 10px;\r\n+  color: #FF6B6B;\r\n }\r\n \r\n #task-list {\r\n-    list-style-type: decimal;\r\n-    padding-left: 20px;\r\n+  list-style-type: decimal;\r\n+  padding-left: 20px;\r\n }\r\n \r\n+/* Task items */\r\n .task-item {\r\n-    display: flex;\r\n-    justify-content: space-between;\r\n-    align-items: center;\r\n-    padding: 10px 5px;\r\n-    border-bottom: 1px dashed #FFD93D;\r\n+  display: flex;\r\n+  justify-content: space-between;\r\n+  align-items: center;\r\n+  padding: 10px 5px;\r\n+  border-bottom: 1px dashed #FFD93D;\r\n+  transition: color 0.3s ease;\r\n }\r\n \r\n .task-item span {\r\n-    flex-grow: 1;\r\n-    font-size: 18px;\r\n+  flex-grow: 1;\r\n+  font-size: 18px;\r\n }\r\n \r\n-/* Completed task style */\r\n .completed span {\r\n-    text-decoration: line-through;\r\n-    color: #999;\r\n-    opacity: 0.7;\r\n+  text-decoration: line-through;\r\n+  color: #999;\r\n+  opacity: 0.7;\r\n }\r\n \r\n-/* Buttons inside task items */\r\n+/* Buttons on task */\r\n .complete-btn,\r\n .remove-btn {\r\n-    margin-left: 10px;\r\n-    padding: 6px 10px;\r\n-    font-size: 14px;\r\n-    border: none;\r\n-    border-radius: 6px;\r\n-    cursor: pointer;\r\n-    transition: all 0.2s ease;\r\n+  margin-left: 10px;\r\n+  padding: 6px 10px;\r\n+  font-size: 14px;\r\n+  border: none;\r\n+  border-radius: 6px;\r\n+  cursor: pointer;\r\n+  transition: all 0.2s ease;\r\n }\r\n \r\n-/* Complete button - green */\r\n .complete-btn {\r\n-    background-color: #6BCB77;\r\n-    color: white;\r\n+  background-color: #6BCB77;\r\n+  color: white;\r\n }\r\n \r\n .complete-btn:hover {\r\n-    background-color: #4CAF50;\r\n+  background-color: #4CAF50;\r\n }\r\n \r\n-/* Remove button - yellow */\r\n .remove-btn {\r\n-    background-color: #FFD93D;\r\n-    color: #333;\r\n+  background-color: #FFD93D;\r\n+  color: #333;\r\n }\r\n \r\n .remove-btn:hover {\r\n-    background-color: #FEC601;\r\n+  background-color: #FEC601;\r\n }\r\n \r\n /* Footer */\r\n footer#ft {\r\n-    text-align: center;\r\n-    font-size: 14px;\r\n-    margin-top: 30px;\r\n-    color: #888;\r\n+  text-align: center;\r\n+  font-size: 14px;\r\n+  margin-top: 30px;\r\n+  color: #888;\r\n }\r\n \r\n+/* Error message style */\r\n+.error-msg {\r\n+  color: #ff4b5c;\r\n+  font-size: 14px;\r\n+  margin-top: 6px;\r\n+  font-weight: 600;\r\n+  font-family: 'Segoe UI', Tahoma, Geneva, Verdana, sans-serif;\r\n+}\r\n+\r\n+.hidden {\r\n+  display: none;\r\n+}\r\n+\r\n+/* Dark mode styles */\r\n+#container.dark-mode {\r\n+  background-color: #1E1E2F;\r\n+  color: #eee;\r\n+  box-shadow: 0 5px 15px rgba(255, 255, 255, 0.1);\r\n+}\r\n+\r\n+#container.dark-mode header#hd {\r\n+  border-bottom: 1px solid #444;\r\n+}\r\n+\r\n+#container.dark-mode #task-input {\r\n+  background-color: #333;\r\n+  border-color: #555;\r\n+  color: #eee;\r\n+}\r\n+\r\n+#container.dark-mode #task-input::placeholder {\r\n+  color: #bbb;\r\n+}\r\n+\r\n+#container.dark-mode #add-task-btn {\r\n+  background-color: #4a90e2;\r\n+}\r\n+\r\n+#container.dark-mode #add-task-btn:hover {\r\n+  background-color: #357ABD;\r\n+}\r\n+\r\n+#container.dark-mode .mn__sect h2 {\r\n+  color: #4a90e2;\r\n+}\r\n+\r\n+#container.dark-mode #task-list {\r\n+  color: #eee;\r\n+}\r\n+\r\n+#container.dark-mode .task-item {\r\n+  border-bottom: 1px dashed #4a90e2;\r\n+}\r\n+\r\n+#container.dark-mode .task-item.completed span {\r\n+  color: #777;\r\n+}\r\n+\r\n+#container.dark-mode .complete-btn {\r\n+  background-color: #6BCB77;\r\n+  color: #1E1E2F;\r\n+}\r\n+\r\n+#container.dark-mode .complete-btn:hover {\r\n+  background-color: #4CAF50;\r\n+}\r\n+\r\n+#container.dark-mode .remove-btn {\r\n+  background-color: #FFD93D;\r\n+  color: #1E1E2F;\r\n+}\r\n+\r\n+#container.dark-mode .remove-btn:hover {\r\n+  background-color: #FEC601;\r\n+}\r\n+\r\n+#container.dark-mode footer#ft {\r\n+  color: #aaa;\r\n+}\r\n+\r\n+#container.dark-mode .error-msg {\r\n+  color: #FF6B6B;\r\n+}\r\n"
                },
                {
                    "date": 1753048906668,
                    "content": "Index: \n===================================================================\n--- \n+++ \n@@ -1,32 +1,30 @@\n-/* Reset & base */\r\n * {\r\n   margin: 0;\r\n   padding: 0;\r\n   box-sizing: border-box;\r\n-  font-family: 'Comic Neue', 'Segoe UI', sans-serif;\r\n+  font-family: 'Segoe UI', sans-serif;\r\n }\r\n \r\n body {\r\n-  background-color: #FFF7E9;\r\n+  background-color: #fff7e9;\r\n   color: #333;\r\n }\r\n \r\n #container {\r\n   max-width: 600px;\r\n   margin: 40px auto;\r\n   padding: 25px;\r\n-  background-color: #FFFBF5;\r\n+  background-color: #fffbf5;\r\n   border-radius: 16px;\r\n   box-shadow: 0 5px 15px rgba(0,0,0,0.1);\r\n   transition: background-color 0.3s ease, color 0.3s ease;\r\n }\r\n \r\n-/* Header */\r\n header#hd {\r\n   display: flex;\r\n+  justify-content: center;\r\n   align-items: center;\r\n-  justify-content: center;\r\n   gap: 15px;\r\n   margin-bottom: 25px;\r\n }\r\n \r\n@@ -37,200 +35,181 @@\n #dark-mode-toggle {\r\n   background: none;\r\n   border: none;\r\n   cursor: pointer;\r\n-  font-size: 28px;\r\n-  color: #FF6B6B;\r\n+  font-size: 24px;\r\n+  color: #ff6b6b;\r\n   transition: color 0.3s ease;\r\n }\r\n \r\n #dark-mode-toggle:hover {\r\n-  color: #FF4B5C;\r\n+  color: #ff4b5c;\r\n }\r\n \r\n-/* Input and button */\r\n #task-input {\r\n   width: 70%;\r\n   padding: 10px;\r\n-  border: 2px solid #FFB6B6;\r\n+  border: 2px solid #ffb6b6;\r\n   border-radius: 8px;\r\n   font-size: 16px;\r\n   background-color: #fff;\r\n-  color: #333;\r\n-  transition: border-color 0.3s ease;\r\n }\r\n \r\n-#task-input:focus {\r\n-  border-color: #FF6B6B;\r\n-  outline: none;\r\n-}\r\n-\r\n #add-task-btn {\r\n   padding: 10px 15px;\r\n-  background-color: #FF6B6B;\r\n+  background-color: #ff6b6b;\r\n   color: white;\r\n   border: none;\r\n   font-size: 16px;\r\n   border-radius: 8px;\r\n   cursor: pointer;\r\n   margin-left: 10px;\r\n-  transition: background-color 0.3s ease;\r\n }\r\n \r\n #add-task-btn:hover {\r\n-  background-color: #FF4B5C;\r\n+  background-color: #ff4b5c;\r\n }\r\n \r\n-/* Sections */\r\n .mn__sect h2 {\r\n   font-size: 22px;\r\n   margin-bottom: 10px;\r\n-  color: #FF6B6B;\r\n+  color: #ff6b6b;\r\n }\r\n \r\n #task-list {\r\n-  list-style-type: decimal;\r\n-  padding-left: 20px;\r\n+  list-style-type: none;\r\n+  padding-left: 0;\r\n }\r\n \r\n-/* Task items */\r\n .task-item {\r\n   display: flex;\r\n   justify-content: space-between;\r\n   align-items: center;\r\n-  padding: 10px 5px;\r\n-  border-bottom: 1px dashed #FFD93D;\r\n-  transition: color 0.3s ease;\r\n+  background-color: #fff5f5;\r\n+  padding: 12px 16px;\r\n+  margin-bottom: 12px;\r\n+  border-radius: 10px;\r\n+  box-shadow: 0 2px 6px rgba(0, 0, 0, 0.05);\r\n+  transition: background-color 0.3s ease, transform 0.2s ease;\r\n }\r\n \r\n+.task-item:hover {\r\n+  background-color: #ffecec;\r\n+  transform: scale(1.01);\r\n+}\r\n+\r\n .task-item span {\r\n   flex-grow: 1;\r\n   font-size: 18px;\r\n+  padding-right: 10px;\r\n }\r\n \r\n .completed span {\r\n   text-decoration: line-through;\r\n   color: #999;\r\n   opacity: 0.7;\r\n }\r\n \r\n-/* Buttons on task */\r\n .complete-btn,\r\n .remove-btn {\r\n   margin-left: 10px;\r\n   padding: 6px 10px;\r\n   font-size: 14px;\r\n   border: none;\r\n   border-radius: 6px;\r\n   cursor: pointer;\r\n-  transition: all 0.2s ease;\r\n }\r\n \r\n .complete-btn {\r\n-  background-color: #6BCB77;\r\n+  background-color: #6bcb77;\r\n   color: white;\r\n }\r\n \r\n .complete-btn:hover {\r\n-  background-color: #4CAF50;\r\n+  background-color: #4caf50;\r\n }\r\n \r\n .remove-btn {\r\n-  background-color: #FFD93D;\r\n+  background-color: #ffd93d;\r\n   color: #333;\r\n }\r\n \r\n .remove-btn:hover {\r\n-  background-color: #FEC601;\r\n+  background-color: #fec601;\r\n }\r\n \r\n-/* Footer */\r\n footer#ft {\r\n   text-align: center;\r\n   font-size: 14px;\r\n   margin-top: 30px;\r\n   color: #888;\r\n }\r\n \r\n-/* Error message style */\r\n .error-msg {\r\n   color: #ff4b5c;\r\n   font-size: 14px;\r\n   margin-top: 6px;\r\n   font-weight: 600;\r\n-  font-family: 'Segoe UI', Tahoma, Geneva, Verdana, sans-serif;\r\n }\r\n \r\n .hidden {\r\n   display: none;\r\n }\r\n \r\n-/* Dark mode styles */\r\n+/* Dark Mode */\r\n #container.dark-mode {\r\n-  background-color: #1E1E2F;\r\n+  background-color: #1e1e2f;\r\n   color: #eee;\r\n-  box-shadow: 0 5px 15px rgba(255, 255, 255, 0.1);\r\n }\r\n \r\n-#container.dark-mode header#hd {\r\n-  border-bottom: 1px solid #444;\r\n-}\r\n-\r\n #container.dark-mode #task-input {\r\n   background-color: #333;\r\n   border-color: #555;\r\n   color: #eee;\r\n }\r\n \r\n #container.dark-mode #task-input::placeholder {\r\n-  color: #bbb;\r\n+  color: #aaa;\r\n }\r\n \r\n #container.dark-mode #add-task-btn {\r\n   background-color: #4a90e2;\r\n }\r\n \r\n #container.dark-mode #add-task-btn:hover {\r\n-  background-color: #357ABD;\r\n+  background-color: #357abd;\r\n }\r\n \r\n #container.dark-mode .mn__sect h2 {\r\n   color: #4a90e2;\r\n }\r\n \r\n-#container.dark-mode #task-list {\r\n-  color: #eee;\r\n+#container.dark-mode .task-item {\r\n+  background-color: #2c2c3e;\r\n+  box-shadow: 0 2px 6px rgba(255, 255, 255, 0.05);\r\n }\r\n \r\n-#container.dark-mode .task-item {\r\n-  border-bottom: 1px dashed #4a90e2;\r\n+#container.dark-mode .task-item:hover {\r\n+  background-color: #3a3a52;\r\n }\r\n \r\n-#container.dark-mode .task-item.completed span {\r\n+#container.dark-mode .completed span {\r\n   color: #777;\r\n }\r\n \r\n #container.dark-mode .complete-btn {\r\n-  background-color: #6BCB77;\r\n-  color: #1E1E2F;\r\n+  background-color: #6bcb77;\r\n+  color: #1e1e2f;\r\n }\r\n \r\n-#container.dark-mode .complete-btn:hover {\r\n-  background-color: #4CAF50;\r\n-}\r\n-\r\n #container.dark-mode .remove-btn {\r\n-  background-color: #FFD93D;\r\n-  color: #1E1E2F;\r\n+  background-color: #ffd93d;\r\n+  color: #1e1e2f;\r\n }\r\n \r\n-#container.dark-mode .remove-btn:hover {\r\n-  background-color: #FEC601;\r\n+#container.dark-mode .error-msg {\r\n+  color: #ff6b6b;\r\n }\r\n \r\n #container.dark-mode footer#ft {\r\n   color: #aaa;\r\n }\r\n-\r\n-#container.dark-mode .error-msg {\r\n-  color: #FF6B6B;\r\n-}\r\n"
                },
                {
                    "date": 1753049321870,
                    "content": "Index: \n===================================================================\n--- \n+++ \n@@ -1,9 +1,9 @@\n * {\r\n   margin: 0;\r\n   padding: 0;\r\n   box-sizing: border-box;\r\n-  font-family: 'Segoe UI', sans-serif;\r\n+  font-family: \"Segoe UI\", sans-serif;\r\n }\r\n \r\n body {\r\n   background-color: #fff7e9;\r\n@@ -15,81 +15,72 @@\n   margin: 40px auto;\r\n   padding: 25px;\r\n   background-color: #fffbf5;\r\n   border-radius: 16px;\r\n-  box-shadow: 0 5px 15px rgba(0,0,0,0.1);\r\n+  box-shadow: 0 5px 15px rgba(0, 0, 0, 0.1);\r\n   transition: background-color 0.3s ease, color 0.3s ease;\r\n }\r\n \r\n header#hd {\r\n   display: flex;\r\n-  justify-content: center;\r\n+  justify-content: space-between;\r\n   align-items: center;\r\n-  gap: 15px;\r\n   margin-bottom: 25px;\r\n }\r\n \r\n #logo {\r\n-  width: 120px;\r\n+  width: 110px;\r\n }\r\n \r\n #dark-mode-toggle {\r\n   background: none;\r\n   border: none;\r\n   cursor: pointer;\r\n   font-size: 24px;\r\n-  color: #ff6b6b;\r\n-  transition: color 0.3s ease;\r\n }\r\n \r\n-#dark-mode-toggle:hover {\r\n-  color: #ff4b5c;\r\n-}\r\n-\r\n #task-input {\r\n-  width: 70%;\r\n+  width: 100%;\r\n   padding: 10px;\r\n   border: 2px solid #ffb6b6;\r\n   border-radius: 8px;\r\n+  margin-bottom: 10px;\r\n   font-size: 16px;\r\n-  background-color: #fff;\r\n }\r\n \r\n #add-task-btn {\r\n-  padding: 10px 15px;\r\n+  width: 100%;\r\n+  padding: 10px;\r\n   background-color: #ff6b6b;\r\n   color: white;\r\n   border: none;\r\n   font-size: 16px;\r\n   border-radius: 8px;\r\n   cursor: pointer;\r\n-  margin-left: 10px;\r\n+  margin-bottom: 10px;\r\n }\r\n \r\n #add-task-btn:hover {\r\n   background-color: #ff4b5c;\r\n }\r\n \r\n-.mn__sect h2 {\r\n+#mn__sect02 h2 {\r\n   font-size: 22px;\r\n+  color: #ff6b6b;\r\n   margin-bottom: 10px;\r\n-  color: #ff6b6b;\r\n }\r\n \r\n #task-list {\r\n   list-style-type: none;\r\n   padding-left: 0;\r\n }\r\n \r\n .task-item {\r\n-  display: flex;\r\n-  justify-content: space-between;\r\n-  align-items: center;\r\n   background-color: #fff5f5;\r\n-  padding: 12px 16px;\r\n+  padding: 14px;\r\n   margin-bottom: 12px;\r\n-  border-radius: 10px;\r\n-  box-shadow: 0 2px 6px rgba(0, 0, 0, 0.05);\r\n+  border-radius: 12px;\r\n+  box-shadow: 0 4px 10px rgba(0, 0, 0, 0.05);\r\n   transition: background-color 0.3s ease, transform 0.2s ease;\r\n }\r\n \r\n .task-item:hover {\r\n@@ -97,65 +88,56 @@\n   transform: scale(1.01);\r\n }\r\n \r\n .task-item span {\r\n-  flex-grow: 1;\r\n+  display: block;\r\n   font-size: 18px;\r\n-  padding-right: 10px;\r\n+  margin-bottom: 10px;\r\n }\r\n \r\n-.completed span {\r\n+.task-item.completed span {\r\n   text-decoration: line-through;\r\n   color: #999;\r\n   opacity: 0.7;\r\n }\r\n \r\n .complete-btn,\r\n .remove-btn {\r\n-  margin-left: 10px;\r\n-  padding: 6px 10px;\r\n-  font-size: 14px;\r\n+  padding: 8px 10px;\r\n+  margin-right: 10px;\r\n   border: none;\r\n   border-radius: 6px;\r\n   cursor: pointer;\r\n+  font-size: 14px;\r\n }\r\n \r\n .complete-btn {\r\n   background-color: #6bcb77;\r\n   color: white;\r\n }\r\n \r\n-.complete-btn:hover {\r\n-  background-color: #4caf50;\r\n-}\r\n-\r\n .remove-btn {\r\n   background-color: #ffd93d;\r\n   color: #333;\r\n }\r\n \r\n-.remove-btn:hover {\r\n-  background-color: #fec601;\r\n-}\r\n-\r\n-footer#ft {\r\n-  text-align: center;\r\n-  font-size: 14px;\r\n-  margin-top: 30px;\r\n-  color: #888;\r\n-}\r\n-\r\n .error-msg {\r\n   color: #ff4b5c;\r\n   font-size: 14px;\r\n-  margin-top: 6px;\r\n   font-weight: 600;\r\n }\r\n \r\n .hidden {\r\n   display: none;\r\n }\r\n \r\n+footer#ft {\r\n+  text-align: center;\r\n+  font-size: 14px;\r\n+  margin-top: 30px;\r\n+  color: #888;\r\n+}\r\n+\r\n /* Dark Mode */\r\n #container.dark-mode {\r\n   background-color: #1e1e2f;\r\n   color: #eee;\r\n@@ -174,42 +156,57 @@\n #container.dark-mode #add-task-btn {\r\n   background-color: #4a90e2;\r\n }\r\n \r\n-#container.dark-mode #add-task-btn:hover {\r\n-  background-color: #357abd;\r\n-}\r\n-\r\n-#container.dark-mode .mn__sect h2 {\r\n+#container.dark-mode #mn__sect02 h2 {\r\n   color: #4a90e2;\r\n }\r\n \r\n #container.dark-mode .task-item {\r\n   background-color: #2c2c3e;\r\n-  box-shadow: 0 2px 6px rgba(255, 255, 255, 0.05);\r\n }\r\n \r\n #container.dark-mode .task-item:hover {\r\n   background-color: #3a3a52;\r\n }\r\n \r\n-#container.dark-mode .completed span {\r\n-  color: #777;\r\n+#container.dark-mode .task-item span {\r\n+  color: #eee;\r\n }\r\n \r\n-#container.dark-mode .complete-btn {\r\n-  background-color: #6bcb77;\r\n-  color: #1e1e2f;\r\n+#container.dark-mode .error-msg {\r\n+  color: #ff6b6b;\r\n }\r\n \r\n-#container.dark-mode .remove-btn {\r\n-  background-color: #ffd93d;\r\n-  color: #1e1e2f;\r\n-}\r\n+/* Mobile */\r\n+@media (max-width: 600px) {\r\n+  #task-input,\r\n+  #add-task-btn {\r\n+    width: 100%;\r\n+  }\r\n \r\n-#container.dark-mode .error-msg {\r\n-  color: #ff6b6b;\r\n+  .task-item span {\r\n+    font-size: 16px;\r\n+  }\r\n+\r\n+  .complete-btn,\r\n+  .remove-btn {\r\n+    width: 100%;\r\n+    margin: 5px 0 0 0;\r\n+  }\r\n }\r\n \r\n-#container.dark-mode footer#ft {\r\n-  color: #aaa;\r\n+/* Tablet */\r\n+@media (min-width: 601px) and (max-width: 1024px) {\r\n+  #task-input {\r\n+    width: 65%;\r\n+  }\r\n+\r\n+  #add-task-btn {\r\n+    width: 30%;\r\n+    margin-left: 5%;\r\n+  }\r\n+\r\n+  .task-item {\r\n+    flex-direction: column;\r\n+  }\r\n }\r\n"
                },
                {
                    "date": 1753051807355,
                    "content": "Index: \n===================================================================\n--- \n+++ \n@@ -19,26 +19,31 @@\n   box-shadow: 0 5px 15px rgba(0, 0, 0, 0.1);\r\n   transition: background-color 0.3s ease, color 0.3s ease;\r\n }\r\n \r\n+/* === Header & Logo Centered === */\r\n header#hd {\r\n   display: flex;\r\n-  justify-content: space-between;\r\n+  justify-content: center;\r\n   align-items: center;\r\n   margin-bottom: 25px;\r\n }\r\n \r\n #logo {\r\n-  width: 110px;\r\n+  display: flex;\r\n+  align-items: center;\r\n+  gap: 10px;\r\n+  font-size: 30px;\r\n+  font-weight: bold;\r\n+  color: #ff6b6b;\r\n }\r\n \r\n-#dark-mode-toggle {\r\n-  background: none;\r\n-  border: none;\r\n-  cursor: pointer;\r\n-  font-size: 24px;\r\n+#logo .checkmark {\r\n+  color: #ffd93d;\r\n+  font-size: 28px;\r\n }\r\n \r\n+/* === Input & Button === */\r\n #task-input {\r\n   width: 100%;\r\n   padding: 10px;\r\n   border: 2px solid #ffb6b6;\r\n@@ -62,8 +67,9 @@\n #add-task-btn:hover {\r\n   background-color: #ff4b5c;\r\n }\r\n \r\n+/* === Task Section === */\r\n #mn__sect02 h2 {\r\n   font-size: 22px;\r\n   color: #ff6b6b;\r\n   margin-bottom: 10px;\r\n@@ -136,9 +142,9 @@\n   margin-top: 30px;\r\n   color: #888;\r\n }\r\n \r\n-/* Dark Mode */\r\n+/* === Dark Mode Support === */\r\n #container.dark-mode {\r\n   background-color: #1e1e2f;\r\n   color: #eee;\r\n }\r\n@@ -176,9 +182,9 @@\n #container.dark-mode .error-msg {\r\n   color: #ff6b6b;\r\n }\r\n \r\n-/* Mobile */\r\n+/* === Responsive Design === */\r\n @media (max-width: 600px) {\r\n   #task-input,\r\n   #add-task-btn {\r\n     width: 100%;\r\n@@ -194,9 +200,8 @@\n     margin: 5px 0 0 0;\r\n   }\r\n }\r\n \r\n-/* Tablet */\r\n @media (min-width: 601px) and (max-width: 1024px) {\r\n   #task-input {\r\n     width: 65%;\r\n   }\r\n"
                },
                {
                    "date": 1753051924149,
                    "content": "Index: \n===================================================================\n--- \n+++ \n@@ -19,31 +19,26 @@\n   box-shadow: 0 5px 15px rgba(0, 0, 0, 0.1);\r\n   transition: background-color 0.3s ease, color 0.3s ease;\r\n }\r\n \r\n-/* === Header & Logo Centered === */\r\n header#hd {\r\n   display: flex;\r\n-  justify-content: center;\r\n+  justify-content: space-between;\r\n   align-items: center;\r\n   margin-bottom: 25px;\r\n }\r\n \r\n #logo {\r\n-  display: flex;\r\n-  align-items: center;\r\n-  gap: 10px;\r\n-  font-size: 30px;\r\n-  font-weight: bold;\r\n-  color: #ff6b6b;\r\n+  width: 110px;\r\n }\r\n \r\n-#logo .checkmark {\r\n-  color: #ffd93d;\r\n-  font-size: 28px;\r\n+#dark-mode-toggle {\r\n+  background: none;\r\n+  border: none;\r\n+  cursor: pointer;\r\n+  font-size: 24px;\r\n }\r\n \r\n-/* === Input & Button === */\r\n #task-input {\r\n   width: 100%;\r\n   padding: 10px;\r\n   border: 2px solid #ffb6b6;\r\n@@ -67,9 +62,8 @@\n #add-task-btn:hover {\r\n   background-color: #ff4b5c;\r\n }\r\n \r\n-/* === Task Section === */\r\n #mn__sect02 h2 {\r\n   font-size: 22px;\r\n   color: #ff6b6b;\r\n   margin-bottom: 10px;\r\n@@ -142,9 +136,9 @@\n   margin-top: 30px;\r\n   color: #888;\r\n }\r\n \r\n-/* === Dark Mode Support === */\r\n+/* Dark Mode */\r\n #container.dark-mode {\r\n   background-color: #1e1e2f;\r\n   color: #eee;\r\n }\r\n@@ -182,9 +176,9 @@\n #container.dark-mode .error-msg {\r\n   color: #ff6b6b;\r\n }\r\n \r\n-/* === Responsive Design === */\r\n+/* Mobile */\r\n @media (max-width: 600px) {\r\n   #task-input,\r\n   #add-task-btn {\r\n     width: 100%;\r\n@@ -200,8 +194,9 @@\n     margin: 5px 0 0 0;\r\n   }\r\n }\r\n \r\n+/* Tablet */\r\n @media (min-width: 601px) and (max-width: 1024px) {\r\n   #task-input {\r\n     width: 65%;\r\n   }\r\n@@ -213,5 +208,5 @@\n \r\n   .task-item {\r\n     flex-direction: column;\r\n   }\r\n-}\r\n+}\n\\ No newline at end of file\n"
                },
                {
                    "date": 1753052319806,
                    "content": "Index: \n===================================================================\n--- \n+++ \n@@ -19,26 +19,39 @@\n   box-shadow: 0 5px 15px rgba(0, 0, 0, 0.1);\r\n   transition: background-color 0.3s ease, color 0.3s ease;\r\n }\r\n \r\n+/* ✅ Header with full-size image */\r\n header#hd {\r\n-  display: flex;\r\n-  justify-content: space-between;\r\n-  align-items: center;\r\n+  position: relative;\r\n   margin-bottom: 25px;\r\n+  height: 150px;\r\n+  border-radius: 12px;\r\n+  overflow: hidden;\r\n }\r\n \r\n-#logo {\r\n-  width: 110px;\r\n+#header-banner {\r\n+  width: 100%;\r\n+  height: 100%;\r\n+  object-fit: cover;\r\n+  display: block;\r\n }\r\n \r\n+/* 🌙 Dark mode toggle positioned top right */\r\n #dark-mode-toggle {\r\n-  background: none;\r\n+  position: absolute;\r\n+  top: 10px;\r\n+  right: 10px;\r\n+  background: rgba(255, 255, 255, 0.8);\r\n   border: none;\r\n   cursor: pointer;\r\n   font-size: 24px;\r\n+  border-radius: 8px;\r\n+  padding: 5px 10px;\r\n }\r\n \r\n+/* --- باقي التنسيقات كما هي --- */\r\n+\r\n #task-input {\r\n   width: 100%;\r\n   padding: 10px;\r\n   border: 2px solid #ffb6b6;\r\n@@ -208,5 +221,5 @@\n \r\n   .task-item {\r\n     flex-direction: column;\r\n   }\r\n-}\n\\ No newline at end of file\n+}\r\n"
                },
                {
                    "date": 1753052923366,
                    "content": "Index: \n===================================================================\n--- \n+++ \n@@ -18,9 +18,16 @@\n   border-radius: 16px;\r\n   box-shadow: 0 5px 15px rgba(0, 0, 0, 0.1);\r\n   transition: background-color 0.3s ease, color 0.3s ease;\r\n }\r\n+#logo img {\r\n+  max-width: 100%;   /* لا تزيد عن عرض الحاوية */\r\n+  height: auto;      /* لتحافظ على نسبة الارتفاع */\r\n+  display: block;\r\n+  margin: 0 auto;    /* لتمركز الصورة أفقياً */\r\n+}\r\n \r\n+\r\n /* ✅ Header with full-size image */\r\n header#hd {\r\n   position: relative;\r\n   margin-bottom: 25px;\r\n"
                }
            ],
            "date": 1753046481037,
            "name": "Commit-0",
            "content": "/* Reset some default styles */\r\n* {\r\n    margin: 0;\r\n    padding: 0;\r\n    box-sizing: border-box;\r\n    font-family: Arial, sans-serif;\r\n}\r\n\r\nbody {\r\n    background-color: #f0f2f5;\r\n    color: #333;\r\n}\r\n\r\n#container {\r\n    max-width: 600px;\r\n    margin: 40px auto;\r\n    padding: 20px;\r\n    background-color: #fff;\r\n    border-radius: 12px;\r\n    box-shadow: 0 2px 8px rgba(0,0,0,0.1);\r\n}\r\n\r\nheader#hd {\r\n    text-align: center;\r\n    margin-bottom: 20px;\r\n}\r\n\r\n#logo {\r\n    width: 120px;\r\n}\r\n\r\n.mn__sect {\r\n    margin-bottom: 20px;\r\n}\r\n\r\n#task-input {\r\n    width: 70%;\r\n    padding: 10px;\r\n    border: 1px solid #ccc;\r\n    border-radius: 6px;\r\n    font-size: 16px;\r\n}\r\n\r\n#add-task-btn {\r\n    padding: 10px 15px;\r\n    background-color: #007bff;\r\n    color: white;\r\n    border: none;\r\n    font-size: 16px;\r\n    border-radius: 6px;\r\n    cursor: pointer;\r\n    margin-left: 10px;\r\n}\r\n\r\n#add-task-btn:hover {\r\n    background-color: #0056b3;\r\n}\r\n\r\n#task-list {\r\n    list-style-type: decimal;\r\n    padding-left: 20px;\r\n}\r\n\r\n.task-item {\r\n    display: flex;\r\n    justify-content: space-between;\r\n    align-items: center;\r\n    padding: 8px 0;\r\n    border-bottom: 1px solid #eee;\r\n}\r\n\r\n.task-item span {\r\n    flex-grow: 1;\r\n}\r\n\r\n.completed span {\r\n    text-decoration: line-through;\r\n    color: gray;\r\n}\r\n\r\n.complete-btn,\r\n.remove-btn {\r\n    margin-left: 10px;\r\n    padding: 5px 10px;\r\n    font-size: 14px;\r\n    border: none;\r\n    border-radius: 4px;\r\n    cursor: pointer;\r\n}\r\n\r\n.complete-btn {\r\n    background-color: #28a745;\r\n    color: white;\r\n}\r\n\r\n.remove-btn {\r\n    background-color: #dc3545;\r\n    color: white;\r\n}\r\n\r\nfooter#ft {\r\n    text-align: center;\r\n    font-size: 14px;\r\n    margin-top: 30px;\r\n    color: #666;\r\n}\r\n"
        }
    ]
}